chemotools/__init__.py
chemotools/augmentation/__init__.py
chemotools/augmentation/_add_noise.py
chemotools/augmentation/_baseline_shift.py
chemotools/augmentation/_fractional_shift.py
chemotools/augmentation/_gaussian_broadening.py
chemotools/augmentation/_index_shift.py
chemotools/augmentation/_spectrum_scale.py
chemotools/baseline/__init__.py
chemotools/baseline/_air_pls.py
chemotools/baseline/_ar_pls.py
chemotools/baseline/_as_ls.py
chemotools/baseline/_base.py
chemotools/baseline/_constant_baseline_correction.py
chemotools/baseline/_cubic_spline_correction.py
chemotools/baseline/_linear_correction.py
chemotools/baseline/_non_negative.py
chemotools/baseline/_polynomial_correction.py
chemotools/baseline/_subtract_reference.py
chemotools/datasets/__init__.py
chemotools/datasets/_base.py
chemotools/datasets/data/__init__.py
chemotools/datasets/data/coffee_labels.csv
chemotools/datasets/data/coffee_spectra.csv
chemotools/datasets/data/fermentation_hplc.csv
chemotools/datasets/data/fermentation_spectra.csv
chemotools/datasets/data/train_hplc.csv
chemotools/datasets/data/train_spectra.csv
chemotools/derivative/__init__.py
chemotools/derivative/_norris_william.py
chemotools/derivative/_savitzky_golay.py
chemotools/feature_selection/__init__.py
chemotools/feature_selection/_base.py
chemotools/feature_selection/_index_selector.py
chemotools/feature_selection/_range_cut.py
chemotools/feature_selection/_sr_selector.py
chemotools/feature_selection/_vip_selector.py
chemotools/inspector/__init__.py
chemotools/inspector/_pca_inspector.py
chemotools/inspector/_pls_regression_inspector.py
chemotools/inspector/core/__init__.py
chemotools/inspector/core/base.py
chemotools/inspector/core/latent.py
chemotools/inspector/core/regression.py
chemotools/inspector/core/spectra.py
chemotools/inspector/core/summaries.py
chemotools/inspector/core/utils.py
chemotools/inspector/core/validation.py
chemotools/inspector/helpers/__init__.py
chemotools/inspector/helpers/_latent.py
chemotools-0.2.5.dist-info/METADATA
chemotools-0.2.5.dist-info/WHEEL
chemotools-0.2.5.dist-info/licenses/LICENSE
chemotools-0.2.5.dist-info/RECORD
