Metadata-Version: 2.4
Name: chemotools
Version: 0.2.5
Summary: chemotools: A Python Package that Integrates Chemometrics and scikit-learn
Author: Pau Cabaneros
License-Expression: MIT
License-File: LICENSE
Classifier: License :: OSI Approved :: MIT License
Classifier: Operating System :: OS Independent
Classifier: Programming Language :: Python :: 3
Classifier: Programming Language :: Python :: 3.10
Classifier: Programming Language :: Python :: 3.11
Classifier: Programming Language :: Python :: 3.12
Classifier: Programming Language :: Python :: 3.13
Requires-Python: >=3.10
Requires-Dist: matplotlib>=3.10.7
Requires-Dist: numpy<3,>=2.0.0
Requires-Dist: scikit-learn<2,>=1.4.0
Requires-Dist: scipy<2,>=1.11.0
